{
    "id": "301834",
    "ident": "ATN",
    "type": "small_airport",
    "name": "Namatanai Airport",
    "latitude_deg": "-3.6695",
    "longitude_deg": "152.438",
    "elevation_ft": "150",
    "continent": "OC",
    "iso_country": "PG",
    "iso_region": "PG-NIK",
    "municipality": "Namatanai",
    "scheduled_service": "no",
    "gps_code": "AYNX",
    "iata_code": "ATN",
    "local_code": "NTI",
    "home_link": "",
    "wikipedia_link": "https://en.wikipedia.org/wiki/Namatanai_Airport",
    "keywords": ""
}