{
    "id": "301802",
    "ident": "BSP",
    "type": "small_airport",
    "name": "Bensbach Airport",
    "latitude_deg": "-8.85805555556",
    "longitude_deg": "141.259444444",
    "elevation_ft": "30",
    "continent": "OC",
    "iso_country": "PG",
    "iso_region": "PG-WPD",
    "municipality": "Bensbach",
    "scheduled_service": "no",
    "gps_code": "AYBH",
    "iata_code": "BSP",
    "local_code": "BEN",
    "home_link": "",
    "wikipedia_link": "https://en.wikipedia.org/wiki/Bensbach_Airport",
    "keywords": ""
}