{
    "id": "671",
    "ident": "CBD5",
    "type": "closed",
    "name": "Takla Narrows Airport",
    "latitude_deg": "55.1635488669",
    "longitude_deg": "-125.706124306",
    "elevation_ft": "2380",
    "continent": "NA",
    "iso_country": "CA",
    "iso_region": "CA-BC",
    "municipality": "Takla Narrows",
    "scheduled_service": "no",
    "gps_code": "",
    "iata_code": "",
    "local_code": "",
    "home_link": "",
    "wikipedia_link": "https://en.wikipedia.org/wiki/Takla_Narrows_Aerodrome",
    "keywords": "BD5, CBD5, CBD5"
}