{
    "id": "721",
    "ident": "CBT6",
    "type": "small_airport",
    "name": "Quilchena Airport",
    "latitude_deg": "50.1618895996",
    "longitude_deg": "-120.507745743",
    "elevation_ft": "2100",
    "continent": "NA",
    "iso_country": "CA",
    "iso_region": "CA-BC",
    "municipality": "Quilchena",
    "scheduled_service": "no",
    "gps_code": "CBT6",
    "iata_code": "",
    "local_code": "CBT6",
    "home_link": "",
    "wikipedia_link": "https://en.wikipedia.org/wiki/Quilchena_Airport",
    "keywords": "BT6"
}