{
    "id": "44167",
    "ident": "CN-0089",
    "type": "medium_airport",
    "name": "Lianyungang Huaguoshan International Airport",
    "latitude_deg": "34.41406",
    "longitude_deg": "119.17899",
    "elevation_ft": "",
    "continent": "AS",
    "iso_country": "CN",
    "iso_region": "CN-32",
    "municipality": "Lianyungang",
    "scheduled_service": "yes",
    "gps_code": "ZSLG",
    "iata_code": "LYG",
    "local_code": "",
    "home_link": "",
    "wikipedia_link": "https://en.wikipedia.org/wiki/Lianyungang_Huaguoshan_International_Airport",
    "keywords": ""
}