{
    "id": "1729",
    "ident": "CYFB",
    "type": "medium_airport",
    "name": "Iqaluit Airport",
    "latitude_deg": "63.756402",
    "longitude_deg": "-68.555801",
    "elevation_ft": "110",
    "continent": "NA",
    "iso_country": "CA",
    "iso_region": "CA-NU",
    "municipality": "Iqaluit",
    "scheduled_service": "yes",
    "gps_code": "CYFB",
    "iata_code": "YFB",
    "local_code": "",
    "home_link": "",
    "wikipedia_link": "https://en.wikipedia.org/wiki/Iqaluit_Airport",
    "keywords": "Frobisher Bay Air Base",
    "runways": [
        {
            "id": "234923",
            "airport_ref": "1729",
            "airport_ident": "CYFB",
            "length_ft": "8605",
            "width_ft": "200",
            "surface": "ASP",
            "lighted": "1",
            "closed": "0",
            "le_ident": "16",
            "le_latitude_deg": "63.764989",
            "le_longitude_deg": "-68.574718",
            "le_elevation_ft": "110",
            "le_heading_degT": "137",
            "le_displaced_threshold_ft": "",
            "he_ident": "34",
            "he_latitude_deg": "63.748182",
            "he_longitude_deg": "-68.537471",
            "he_elevation_ft": "71",
            "he_heading_degT": "317",
            "he_displaced_threshold_ft": ""
        }
    ]
}