{
    "id": "3519",
    "ident": "KEWB",
    "type": "medium_airport",
    "name": "New Bedford Regional Airport",
    "latitude_deg": "41.67610168457031",
    "longitude_deg": "-70.95690155029297",
    "elevation_ft": "80",
    "continent": "NA",
    "iso_country": "US",
    "iso_region": "US-MA",
    "municipality": "New Bedford",
    "scheduled_service": "yes",
    "gps_code": "KEWB",
    "iata_code": "EWB",
    "local_code": "EWB",
    "home_link": "",
    "wikipedia_link": "https://en.wikipedia.org/wiki/New_Bedford_Regional_Airport",
    "keywords": "",
    "runways": [
        {
            "id": "241877",
            "airport_ref": "3519",
            "airport_ident": "KEWB",
            "length_ft": "5400",
            "width_ft": "150",
            "surface": "ASP",
            "lighted": "1",
            "closed": "0",
            "le_ident": "05",
            "le_latitude_deg": "41.67169952",
            "le_longitude_deg": "-70.96450043",
            "le_elevation_ft": "66",
            "le_heading_degT": "38.3",
            "le_displaced_threshold_ft": "",
            "he_ident": "23",
            "he_latitude_deg": "41.68239975",
            "he_longitude_deg": "-70.95310211",
            "he_elevation_ft": "78",
            "he_heading_degT": "218.3",
            "he_displaced_threshold_ft": ""
        },
        {
            "id": "241878",
            "airport_ref": "3519",
            "airport_ident": "KEWB",
            "length_ft": "5002",
            "width_ft": "75",
            "surface": "ASP",
            "lighted": "1",
            "closed": "0",
            "le_ident": "14",
            "le_latitude_deg": "41.68030167",
            "le_longitude_deg": "-70.96389771",
            "le_elevation_ft": "77",
            "le_heading_degT": "128.6",
            "le_displaced_threshold_ft": "",
            "he_ident": "32",
            "he_latitude_deg": "41.67179871",
            "he_longitude_deg": "-70.94960022",
            "he_elevation_ft": "67",
            "he_heading_degT": "308.6",
            "he_displaced_threshold_ft": ""
        }
    ]
}