{
    "id": "329",
    "ident": "SNJD",
    "type": "small_airport",
    "name": "João Durval Carneiro Airport",
    "latitude_deg": "-12.200694",
    "longitude_deg": "-38.906164",
    "elevation_ft": "781",
    "continent": "SA",
    "iso_country": "BR",
    "iso_region": "BR-BA",
    "municipality": "Feira De Santana",
    "scheduled_service": "yes",
    "gps_code": "SDIY",
    "iata_code": "FEC",
    "local_code": "BA0013",
    "home_link": "",
    "wikipedia_link": "https://en.wikipedia.org/wiki/Feira_de_Santana_Airport",
    "keywords": "SNJD, SBFE"
}