{
    "id": "25823",
    "ident": "WN28",
    "type": "small_airport",
    "name": "Sunny Slope Runway Airport",
    "latitude_deg": "44.9827995300293",
    "longitude_deg": "-87.30950164794922",
    "elevation_ft": "730",
    "continent": "NA",
    "iso_country": "US",
    "iso_region": "US-WI",
    "municipality": "Egg Harbor",
    "scheduled_service": "no",
    "gps_code": "WN28",
    "iata_code": "",
    "local_code": "WN28",
    "home_link": "",
    "wikipedia_link": "",
    "keywords": ""
}